[
    {
        "keyword_order": 413,
        "keyword": "乌克兰在哈尔科夫地区抓捕俄语课教师？"
    },
    {
        "keyword_order": 412,
        "keyword": "中俄以本币结算费用，1卢布等于1元人民币？系误读"
    },
    {
        "keyword_order": 411,
        "keyword": "卡车拦路军车出没，莫斯科生变？假的！"
    },
    {
        "keyword_order": 409,
        "keyword": "乌官方证实俄西部集团军指挥官西切夫已经被俘？"
    },
    {
        "keyword_order": 408,
        "keyword": "加州人需提供疫苗接种和核酸证明才可恢复供电？"
    },
    {
        "keyword_order": 407,
        "keyword": "塔利班指挥官接受CNN采访称将去乌克兰帮助俄罗斯？"
    },
    {
        "keyword_order": 406,
        "keyword": "外网曝“成都一小区业主驾车碾压‘大白’”？假！"
    },
    {
        "keyword_order": 405,
        "keyword": "西班牙农民对警察喷射稻草，抗议环保政策？"
    },
    {
        "keyword_order": 404,
        "keyword": "沙特防长在中国大使馆前被鞭炮声吓跑？实为科威特安保演习画面"
    },
    {
        "keyword_order": 403,
        "keyword": "乌克兰国防部机密文件显示乌军阵亡人数超过7.6万人？"
    },
    {
        "keyword_order": 402,
        "keyword": "| 这是5000年前苏美尔人的铜人？"
    },
    {
        "keyword_order": 401,
        "keyword": "这位“胡子公主”曾经是波斯第一美人？"
    },
    {
        "keyword_order": 400,
        "keyword": "| 英国发明“九宫格”红绿灯？因造成交通混乱被废除？"
    },
    {
        "keyword_order": 399,
        "keyword": "163架F-16战机启程运往乌克兰？"
    },
    {
        "keyword_order": 398,
        "keyword": "德国新规称三月内未接种加强针，会重新变成“未接种者”？"
    },
    {
        "keyword_order": 397,
        "keyword": "泽连斯基的俄罗斯“护照”被曝光？"
    },
    {
        "keyword_order": 396,
        "keyword": "俄军不慎曝光塑料制S-400导弹？"
    },
    {
        "keyword_order": 394,
        "keyword": "美国援助乌克兰的无人机被拿到暗网上出售？"
    },
    {
        "keyword_order": 393,
        "keyword": "特朗普称其机密文件保存在拜登儿子的笔记本电脑上？"
    },
    {
        "keyword_order": 392,
        "keyword": "西方援乌武器仅30%到达前线？其余进了黑市？"
    },
    {
        "keyword_order": 391,
        "keyword": "出于居民健康考虑，秘鲁当局移除5G天线？"
    },
    {
        "keyword_order": 390,
        "keyword": "菲律宾宣布将制定从台湾地区撤侨的计划？菲方已澄清"
    },
    {
        "keyword_order": 389,
        "keyword": "国军事将领到乌克兰增援，返回途中被俄罗斯歼灭？"
    },
    {
        "keyword_order": 388,
        "keyword": "美国国安委员会发言人称“里根”号航母将穿越台海？"
    },
    {
        "keyword_order": 387,
        "keyword": "海滩上出现大量死鱼，系解放军演习所致？与军演无关！"
    },
    {
        "keyword_order": 385,
        "keyword": "10万志愿军赴乌参战？"
    },
    {
        "keyword_order": 384,
        "keyword": "在西班牙的乌克兰难民烧俄罗斯国旗，致3.1万公顷森林被毁？"
    },
    {
        "keyword_order": 383,
        "keyword": "日本自卫队在台湾以东海域拍到中国军机歼-20？"
    },
    {
        "keyword_order": 382,
        "keyword": "解放军演习中两架歼-20互撞坠机？假的！"
    },
    {
        "keyword_order": 381,
        "keyword": "300门自行火炮集结中国沿海？"
    },
    {
        "keyword_order": 380,
        "keyword": "队在班公湖“割让”印度2.5公里？"
    },
    {
        "keyword_order": 378,
        "keyword": "专机舱门边上这小孔是弹孔？"
    },
    {
        "keyword_order": 376,
        "keyword": "是美国众议院议长佩洛西和蔡英文会见现场照吗？"
    },
    {
        "keyword_order": 375,
        "keyword": "中国派出特种兵，以志愿军名义加入俄军？不实！"
    },
    {
        "keyword_order": 351,
        "keyword": "美众议院议长佩洛西已降落至“松山机场”？消息不实！"
    },
    {
        "keyword_order": 352,
        "keyword": "中国和巴基斯坦“密谋阿富汗领土”？阿塔回应：谣言"
    },
    {
        "keyword_order": 353,
        "keyword": "乌克兰政府已向美国资本出售28%的农业用地？"
    },
    {
        "keyword_order": 350,
        "keyword": "世卫总干事谭德塞被国际刑警组织逮捕？"
    },
    {
        "keyword_order": 354,
        "keyword": "世界上第一对孵化器婴儿问世？女性不用再为生产痛苦？"
    },
    {
        "keyword_order": 269,
        "keyword": "英国政府承认“新冠疫苗可以杀死你”？不实！"
    },
    {
        "keyword_order": 355,
        "keyword": "美国得州农场主冒充拜登，把偷渡客当奴隶使唤？"
    },
    {
        "keyword_order": 270,
        "keyword": "英首相候选人特拉斯称若当选，将参与“特别行动”击败俄？"
    },
    {
        "keyword_order": 356,
        "keyword": "日本确定将修改宪法，放开宣战权？"
    },
    {
        "keyword_order": 271,
        "keyword": "乌克兰驻意使馆强制18-60岁男性公民回国参军？"
    },
    {
        "keyword_order": 357,
        "keyword": "羊驼所带抗体可预防新冠全变异株，计划2年后投产？"
    },
    {
        "keyword_order": 272,
        "keyword": "这一视频是意大利农民上街游行抗议环保政策？"
    },
    {
        "keyword_order": 273,
        "keyword": "| 俄战机飞过立陶宛上空，准备对立全面开战？"
    },
    {
        "keyword_order": 358,
        "keyword": "鲍里斯·约翰逊辞去英国首相，将加盟一家中国公司？"
    },
    {
        "keyword_order": 359,
        "keyword": "网传中国公民戴手铐做核酸？实为涉黄窝点抓捕现场"
    },
    {
        "keyword_order": 360,
        "keyword": "德国取消2035年碳中和目标，“环保先锋”政策大倒退？"
    },
    {
        "keyword_order": 275,
        "keyword": "安倍晋三外祖父岸信介将“统一教会”引入日本？"
    },
    {
        "keyword_order": 274,
        "keyword": "乌克兰大量生产女式军装，动员女性参战？"
    },
    {
        "keyword_order": 361,
        "keyword": "| 乌克兰“艾达尔”营指挥官梅尔尼丘克近期被抓获？"
    },
    {
        "keyword_order": 276,
        "keyword": "波兰停止向乌克兰难民发放每日40兹罗提食宿补助？"
    },
    {
        "keyword_order": 277,
        "keyword": "刺杀安倍的枪手是切·格瓦拉粉丝？"
    },
    {
        "keyword_order": 278,
        "keyword": "刺杀安倍晋三的嫌疑人是大学副教授？"
    },
    {
        "keyword_order": 362,
        "keyword": "刺杀安倍晋三的嫌疑人是大学副教授？"
    },
    {
        "keyword_order": 363,
        "keyword": "乌干达现3100万吨金矿，中国公司将开采？没有证据"
    },
    {
        "keyword_order": 364,
        "keyword": "乌克兰用美援武器轰炸俄罗斯境内目标？"
    },
    {
        "keyword_order": 279,
        "keyword": "4个AI机器人在日本实验室杀死29名科学家？"
    },
    {
        "keyword_order": 346,
        "keyword": "| 北约各国对俄乌冲突态度转变，纷纷做好参战准备？"
    },
    {
        "keyword_order": 365,
        "keyword": "| 北极现自然奇观，超级月亮遮挡太阳？"
    },
    {
        "keyword_order": 280,
        "keyword": "欧洲惊现暗藏刀片的乌克兰民族主义海报？"
    },
    {
        "keyword_order": 281,
        "keyword": "泽连斯基自导自演克列缅丘格购物中心遭袭事件？"
    },
    {
        "keyword_order": 334,
        "keyword": "泽连斯基自导自演克列缅丘格购物中心遭袭事件？"
    },
    {
        "keyword_order": 333,
        "keyword": "“天宫课堂”里的太空站是虚假的吗？理由不成立！"
    },
    {
        "keyword_order": 282,
        "keyword": "美将军称为避免“三战”，应将立陶宛逐出北约？"
    },
    {
        "keyword_order": 283,
        "keyword": "美国洛杉矶街头支持堕胎权游行，却被用来抹黑中国"
    },
    {
        "keyword_order": 284,
        "keyword": "波兰总统公开表示要吞并乌克兰西部？"
    },
    {
        "keyword_order": 332,
        "keyword": "视频展示俄高超音速“匕首”导弹摧毁乌地下弹药库？"
    },
    {
        "keyword_order": 285,
        "keyword": "乌克兰4州宣布加入俄罗斯？"
    },
    {
        "keyword_order": 331,
        "keyword": "俄罗斯限制哈萨克斯坦石油运输，哈封锁境内俄煤炭？"
    },
    {
        "keyword_order": 345,
        "keyword": "基辅市议会撤销“1147年修建莫斯科法令”？"
    },
    {
        "keyword_order": 286,
        "keyword": "德国肯德基广告打擦边球引诱“乌克兰小鸡”？"
    },
    {
        "keyword_order": 330,
        "keyword": "普京这样在屏幕前看马克龙拥抱泽连斯基？"
    },
    {
        "keyword_order": 287,
        "keyword": "哈萨克斯坦冻结俄罗斯银行资金？"
    },
    {
        "keyword_order": 329,
        "keyword": "这是下水前的003型航母？实为玩家游戏中搭建模型"
    },
    {
        "keyword_order": 288,
        "keyword": "美国驻伊拉克埃尔比勒领事馆遭无人机袭击？"
    },
    {
        "keyword_order": 328,
        "keyword": "泽连斯基给台湾出主意如何对付大陆？他根本没提台湾！"
    },
    {
        "keyword_order": 327,
        "keyword": "洪都拉斯禁枪但凶杀率世界第一？错，成人最多可持枪3支"
    },
    {
        "keyword_order": 289,
        "keyword": "乌克兰高官承认谎称俄军在乌实施大规模性暴力？"
    },
    {
        "keyword_order": 326,
        "keyword": "乌克兰尼古拉耶夫港遭袭，中粮集团仓储码头被毁？"
    },
    {
        "keyword_order": 290,
        "keyword": "马克龙和默克尔搭桥，普京和泽连斯基已面对面谈判？"
    },
    {
        "keyword_order": 325,
        "keyword": "俄罗斯停止对中国供电？"
    },
    {
        "keyword_order": 347,
        "keyword": "奥巴马演讲谈美国如何干预他国舆论？\n"
    },
    {
        "keyword_order": 291,
        "keyword": "美国众议院议长丈夫因持有儿童色情制品和可卡因被捕？"
    },
    {
        "keyword_order": 292,
        "keyword": "德国政府为乌克兰难民设计野猪形象吉祥物？"
    },
    {
        "keyword_order": 324,
        "keyword": "辉瑞CEO称计划在2023年前削减世界50%人口？"
    },
    {
        "keyword_order": 293,
        "keyword": "这一视频是巴勒斯坦人伪造孩子被以色列警察射杀？"
    },
    {
        "keyword_order": 294,
        "keyword": "乌克兰“第三大城市”议会拒绝配合乌军抵抗俄军？"
    },
    {
        "keyword_order": 323,
        "keyword": "乌克兰历史书籍遭焚毁，是俄军干的吗？"
    },
    {
        "keyword_order": 295,
        "keyword": "乌军错把荷兰国旗当作俄罗斯国旗公开焚烧？"
    },
    {
        "keyword_order": 322,
        "keyword": "俄乌冲突下，美、俄两国“越打越有钱”了？"
    },
    {
        "keyword_order": 296,
        "keyword": "俄军在亚速钢铁厂内发现中文封面《孙子兵法》？"
    },
    {
        "keyword_order": 321,
        "keyword": "中国代表在达沃斯论坛上拒绝为泽连斯基演讲起立鼓掌？"
    },
    {
        "keyword_order": 320,
        "keyword": "盖茨预言猴痘病毒暴发？辉瑞公司提前准备疫苗？"
    },
    {
        "keyword_order": 297,
        "keyword": "在德乌克兰难民烧俄罗斯国旗点燃安置房？"
    },
    {
        "keyword_order": 319,
        "keyword": "《朝鲜日报》报道朝鲜警察枪杀违反防疫规定的工人？没发过"
    },
    {
        "keyword_order": 298,
        "keyword": "俄军炸毁哈尔科夫植物基因库致约16万种子样本被毁？"
    },
    {
        "keyword_order": 318,
        "keyword": "芬兰空军以“卐”字为标志表达对纳粹的支持？"
    },
    {
        "keyword_order": 299,
        "keyword": "乌克兰村民怒怼泽连斯基，劝其勿信北约？"
    },
    {
        "keyword_order": 317,
        "keyword": "这是CNN歪曲中国防疫的“假新闻”？其实是戏仿视频"
    },
    {
        "keyword_order": 300,
        "keyword": "红场阅兵式上，有阵亡俄军家属上街“讨说法”被拍入这则视频？"
    },
    {
        "keyword_order": 316,
        "keyword": "中国公民赴加留学护照被剪？发布者用盗图，账号已注销"
    },
    {
        "keyword_order": 301,
        "keyword": "“法国”医院使用假人充作新冠患者？"
    },
    {
        "keyword_order": 315,
        "keyword": "乌海军副司令遭俄军导弹袭击身亡？"
    },
    {
        "keyword_order": 314,
        "keyword": "印度国会议员拉胡尔·甘地在尼泊尔私会中国大使？印媒澄清"
    },
    {
        "keyword_order": 302,
        "keyword": "乌克兰一大学教授战壕里上网课？"
    },
    {
        "keyword_order": 313,
        "keyword": "防疫政策导致中国沿海船只拥堵无法进港？严重误导！"
    },
    {
        "keyword_order": 303,
        "keyword": "拜登将因身体原因辞职？其子在亚速钢铁厂被擒获？"
    },
    {
        "keyword_order": 312,
        "keyword": "教皇将乌克兰危机归咎于北约，致梵蒂冈贝宝账户被封？"
    },
    {
        "keyword_order": 304,
        "keyword": "泽连斯基桌上放置可卡因？"
    },
    {
        "keyword_order": 311,
        "keyword": "“中国国家电视台”地图展示“俄罗斯陷落后”遭瓜分？"
    },
    {
        "keyword_order": 305,
        "keyword": "俄军13万人在卢甘斯克向乌军投降？"
    },
    {
        "keyword_order": 267,
        "keyword": "美国辉瑞和莫德纳公司CFO在72小时内相继辞职？"
    },
    {
        "keyword_order": 348,
        "keyword": "这一视频是敖德萨居民楼被炸毁？"
    },
    {
        "keyword_order": 306,
        "keyword": "CNN “缝合”加拿大爆炸图片，报道利沃夫大爆炸？"
    },
    {
        "keyword_order": 374,
        "keyword": "拆解“大翻译运动”"
    },
    {
        "keyword_order": 349,
        "keyword": "马克龙称“欧洲要准备20年内接收6000万难民”？"
    },
    {
        "keyword_order": 366,
        "keyword": "俄军在基地用装甲设备拼出嘲讽单词回应美国卫星偷拍？"
    },
    {
        "keyword_order": 307,
        "keyword": "泽连斯基公开承认吸食可卡因？\n"
    },
    {
        "keyword_order": 308,
        "keyword": "俄军强迫乌克兰俘虏吞下国旗臂章？"
    },
    {
        "keyword_order": 309,
        "keyword": "这一视频是俄出动图-160飞机轰炸马里乌波尔？"
    },
    {
        "keyword_order": 310,
        "keyword": "日本决定向乌克兰派遣自卫队？"
    },
    {
        "keyword_order": 367,
        "keyword": "谷歌地图18日起开放俄所有战略要地高清卫星图像？"
    },
    {
        "keyword_order": 335,
        "keyword": "德国三天内驱逐乌克兰驻德大使？"
    },
    {
        "keyword_order": 368,
        "keyword": "乌克兰将与波兰、芬兰等国组建“非军事小北约”？"
    },
    {
        "keyword_order": 336,
        "keyword": "福奇被特殊武装部队逮捕？"
    },
    {
        "keyword_order": 337,
        "keyword": "北约陆军总司令被俄军俘虏？"
    },
    {
        "keyword_order": 369,
        "keyword": "江苏建湖“抗疫物资”在沪被当作“普通商品”倒卖？不实"
    },
    {
        "keyword_order": 370,
        "keyword": "上海一小区组织唱红歌，居民到点齐声骂居委？误传！"
    },
    {
        "keyword_order": 338,
        "keyword": "布恰“死人诈尸”，拍照证明自己“复活”？"
    },
    {
        "keyword_order": 339,
        "keyword": "264名乌克兰海军陆战队士兵向俄军投降？"
    },
    {
        "keyword_order": 371,
        "keyword": "乌克兰立法禁用字母“Z”和“V”？"
    },
    {
        "keyword_order": 340,
        "keyword": "普京讲话直播中断，现场观众高呼反战口号？"
    },
    {
        "keyword_order": 341,
        "keyword": "这画面不是上海新冠感染者集中隔离的场景\n"
    },
    {
        "keyword_order": 372,
        "keyword": "泄露文件显示俄军下令散布乌军虐待战俘视频抹黑乌方？"
    },
    {
        "keyword_order": 373,
        "keyword": "俄罗斯“海鹰-10”无人机配件多来自中国义乌？不实"
    },
    {
        "keyword_order": 342,
        "keyword": "据传“羞辱阵亡俄军士兵母亲”的乌克兰武装分子被俘？"
    },
    {
        "keyword_order": 343,
        "keyword": "乌克兰农民举办展销会出售坦克？"
    },
    {
        "keyword_order": 266,
        "keyword": "乌军办公室现荣誉勋章，乌克兰早已准备攻打克里米亚？"
    },
    {
        "keyword_order": 344,
        "keyword": "7位俄军将领被传在乌克兰阵亡，实情如何？"
    },
    {
        "keyword_order": 263,
        "keyword": "《纽约时报》承认“为使拜登当选而撒谎”？"
    },
    {
        "keyword_order": 259,
        "keyword": "“世界第一狙击手”在乌克兰刚出场就被俄军击毙？"
    },
    {
        "keyword_order": 260,
        "keyword": "保加利亚退出北约支持俄罗斯？"
    },
    {
        "keyword_order": 261,
        "keyword": "波兰铁路工人中断波乌铁路，援乌武器无法前往乌克兰？"
    },
    {
        "keyword_order": 258,
        "keyword": "东航MU5735客机坠毁第一视角影像流出？"
    },
    {
        "keyword_order": 257,
        "keyword": "乌克兰禁止对中国出口D-30KP-2航空发动机？"
    },
    {
        "keyword_order": 256,
        "keyword": "这个乌克兰女孩衔着棒棒糖扛枪上战场？"
    },
    {
        "keyword_order": 255,
        "keyword": "这个中国小朋友做核酸被残忍捅鼻子？"
    },
    {
        "keyword_order": 254,
        "keyword": "俄车臣武装在乌亚速营总部发现红十字药箱装大量美元？"
    },
    {
        "keyword_order": 252,
        "keyword": "尹锡悦支持120小时工作制？主张废除最低工资标准？"
    },
    {
        "keyword_order": 253,
        "keyword": "美国记者中弹后接受采访视频是摆拍？"
    },
    {
        "keyword_order": 251,
        "keyword": "乌军雇佣“危机演员”摆拍露馅？"
    },
    {
        "keyword_order": 250,
        "keyword": "乌克兰农民捕获俄罗斯战机？"
    },
    {
        "keyword_order": 249,
        "keyword": "乌总统泽连斯基获诺贝尔和平奖提名？"
    },
    {
        "keyword_order": 248,
        "keyword": "大量俄罗斯寡头逃往迪拜，客机跑向远东？"
    },
    {
        "keyword_order": 247,
        "keyword": "这一视频是俄罗斯车臣军团到达乌克兰？"
    },
    {
        "keyword_order": 246,
        "keyword": "联合国秘书长古特雷斯警告“美国正在玩火自焚”？"
    },
    {
        "keyword_order": 210,
        "keyword": "慕尼黑最大综合医院宣布不再治疗俄罗斯患者？"
    },
    {
        "keyword_order": 243,
        "keyword": "乌总统称“不指望加入北约，克里米亚和乌东可以谈”？"
    },
    {
        "keyword_order": 244,
        "keyword": "乌克兰驻尼使馆向报名志愿军的尼日利亚人索要路费？"
    },
    {
        "keyword_order": 245,
        "keyword": "泽连斯基8日再发视频，他能自证“在基辅”吗？"
    },
    {
        "keyword_order": 240,
        "keyword": "俄籍在美商人出资“买普京人头”？不真实"
    },
    {
        "keyword_order": 241,
        "keyword": "以色列航空公司允许使用俄罗斯Mir支付系统？"
    },
    {
        "keyword_order": 242,
        "keyword": "遗漏文件揭秘俄军原计划在3月6日结束军事行动？"
    },
    {
        "keyword_order": 237,
        "keyword": "乌克兰人出售从战场上捡来的俄军坦克？"
    },
    {
        "keyword_order": 238,
        "keyword": "德国汉堡当局没收俄罗斯大亨的超级游艇？"
    },
    {
        "keyword_order": 239,
        "keyword": "俄罗斯3月11日正式和世界互联网断开链接？"
    },
    {
        "keyword_order": 235,
        "keyword": "乌克兰国防部被3枚精确制导炸弹夷为平地？"
    },
    {
        "keyword_order": 234,
        "keyword": "乌克兰军“缴获”的俄军口粮为过期食物？"
    },
    {
        "keyword_order": 233,
        "keyword": "俄军总参谋长因作战不力被解职？"
    },
    {
        "keyword_order": 232,
        "keyword": "俄罗斯将向阵亡士兵家属支付1.1万卢布抚恤金？"
    },
    {
        "keyword_order": 230,
        "keyword": "乌克兰“亚速营”给子弹涂猪油，以攻击俄车臣军队？"
    },
    {
        "keyword_order": 231,
        "keyword": "传闻“一天击落6架俄战机”的“基辅幽灵”真容曝光？"
    },
    {
        "keyword_order": 228,
        "keyword": "欧盟飞行员将换上乌军战服参战？"
    },
    {
        "keyword_order": 229,
        "keyword": "为免军机外泄，俄军发海报敦促士兵禁用TikTok？"
    }
]